<?xml version="1.0" encoding="UTF-8"?>
<!DOCTYPE theme PUBLIC "wa-app-theme" "http://www.webasyst.com/wa-content/xml/wa-app-theme.dtd">
<theme id="extreme" system="0" vendor="webasyst" author="Webasyst" app="site" version="1.1.1">
    <name locale="en_US">Extreme</name>
    <name locale="ru_RU">Extreme</name>
    <description locale="ru_RU">Семейство адаптивных тем дизайна.</description>
    <files>
        <file path="index.html">
            <description locale="en_US">Core layout of the CUSTOM theme family</description>
            <description locale="ru_RU">Основной макет тем дизайна семейства CUSTOM</description>
        </file>
        <file path="custom.css">
            <description locale="en_US">Core CSS of the CUSTOM theme family</description>
            <description locale="ru_RU">Основной файл CSS-стилей семейства тем дизайна CUSTOM</description>
        </file>
        <file path="content.html" custom="0">
            <description locale="en_US">Main layout for the Site app content</description>
            <description locale="en_US">Основной вывод приложения «Сайт»</description>
        </file>
        <file path="head.html" custom="0">
            <description locale="en_US">Site app's &lt;head&gt; instructions</description>
            <description locale="en_US">Блок &lt;head&gt; приложения «Сайт»</description>
        </file>
        <file path="page.html">
            <description locale="en_US">Static page content and navigation</description>
            <description locale="ru_RU">Содержимое открытой страницы и навигация по страницам</description>
        </file>
        <file path="login.html" custom="0">
            <description locale="en_US">Login page</description>
            <description locale="ru_RU">Страница входа для пользователей</description>
        </file>
        <file path="signup.html" custom="0">
            <description locale="en_US">Sign up page</description>
            <description locale="ru_RU">Страница регистрации пользователей</description>
        </file>
        <file path="forgotpassword.html" custom="0">
            <description locale="en_US">Forgot password page</description>
            <description locale="ru_RU">Страница сброса пароля</description>
        </file>
        <file path="error.html">
            <description locale="en_US">404 and other errors</description>
            <description locale="ru_RU">404 и другие ошибки</description>
        </file>
        <file path="custom.js" custom="0">
            <description locale="en_US">JS</description>
            <description locale="ru_RU">JS</description>
        </file>
    </files>
    
    <settings>
        <setting var="logo" control_type="image">
            <value>img/logo.png</value>
            <filename>img/logo.*</filename>
            <name locale="en_US">Company Logo</name>
            <name locale="ru_RU">Логотип компании</name>
        </setting>
        <setting var="bg_image" control_type="image">
            <value>img/bg-main.jpg</value>
            <filename>img/bg-main.*</filename>
            <name locale="en_US">background</name>
            <name locale="ru_RU">Фон</name>
        </setting>
        
        <setting var="source_main_menu" control_type="select">
            <value>shop_categories</value>
            <name locale="en_US">Source for the main top menu</name>
            <name locale="ru_RU">Источник для главного верхнего меню</name>
            <options>
                <option value="site_pages">
                    <name locale="en_US">Application «Site» - pages</name>
                    <name locale="ru_RU">Приложение «Сайт» - страницы</name>
                </option>
                <option value="shop_pages">
                    <name locale="en_US">Application «Shop» - pages</name>
                    <name locale="ru_RU">Приложение «Магазин» - страницы</name>
                </option>
                <option value="shop_categories">
                    <name locale="en_US">Application «Shop» - categories</name>
                    <name locale="ru_RU">Приложение «Магазин» - категории</name>
                </option>
            </options>
        </setting>
    </settings>
     <locales>
        <locale>
            <msgid>To home</msgid>
            <msgstr locale="ru_RU">На главную</msgstr>
        </locale>
    </locales>
</theme>
